python_qt6_gtk/__init__.py
python_qt6_gtk/backend/__init__.py
python_qt6_gtk/backend/msqlver.py
python_qt6_gtk/backend/schema.py
python_qt6_gtk/frontend/__init__.py
python_qt6_gtk/frontend/CTKTKTK/main.py
python_qt6_gtk/frontend/CTKTKTK/order_form.py
python_qt6_gtk-0.1.4.dist-info/METADATA
python_qt6_gtk-0.1.4.dist-info/WHEEL
python_qt6_gtk-0.1.4.dist-info/top_level.txt
python_qt6_gtk-0.1.4.dist-info/RECORD
